{
  "petition": {
    "tid": 194020500,
    "catids": null,
    "doctype": 1004,
    "publishdate": "2023-03-29",
    "authorid": null,
    "bench": [
      455,
      410
    ],
    "title": "Modi Car Agencies Pvt Ltd vs The State Of Maharashtra And 2 Ors on 29 March, 2023",
    "numcites": 9,
    "numcitedby": 64,
    "headline": "",
    "docsize": 17787,
    "fragment": true,
    "docsource": "Bombay High Court"
  },
  "document": "{\"tid\":194020500,\"publishdate\":\"2023-03-29\",\"title\":\"Modi Car Agencies Pvt Ltd vs The State Of Maharashtra And 2 Ors on 29 March, 2023\",\"doc\":\"<h2 class=\\\"doc_title\\\">Modi Car Agencies Pvt Ltd vs The State Of Maharashtra And 2 Ors on 29 March, 2023</h2>\\n\\n<h3 class=\\\"doc_bench\\\">Bench: <a href=\\\"/search/?formInput=benchid:n-m-jamdar\\\">Nitin Jamdar</a>, <a href=\\\"/search/?formInput=benchid:a-ahuja\\\">Abhay Ahuja</a></h3>\\n\\n<pre id=\\\"pre_1\\\">                                                                      Board Sr.No.:-1\\n\\n IN THE HIGH COURT OF JUDICATURE AT BOMBAY\\n     ORDINARY ORIGINAL CIVIL JURISDICTION\\n\\n                WRIT PETITION NO. 2512 OF 2021\\n\\n Modi Car Agencies Pvt. Ltd.                  ....PETITIONER\\n             V/S\\n The State Of Maharashtra And 2 Ors.        ....RESPONDENT</pre>\\n\\n<p data-structure=\\\"RespArg\\\" id=\\\"p_1\\\">                            <span class=\\\"citetext\\\" data-sentiment=\\\"Neg\\\" data-docid=\\\"12976213\\\" id=\\\"span_1\\\"><span class=\\\"citetext\\\" data-sentiment=\\\"Neg\\\" data-docid=\\\"146202757\\\" id=\\\"span_2\\\"><span class=\\\"citetext\\\" data-sentiment=\\\"Neg\\\" data-docid=\\\"77312902\\\" id=\\\"span_3\\\"><span class=\\\"citetext\\\" data-sentiment=\\\"Neg\\\" data-docid=\\\"111103709\\\" id=\\\"span_4\\\"><span class=\\\"citetext\\\" data-sentiment=\\\"Neg\\\" data-docid=\\\"165087826\\\" id=\\\"span_5\\\"><span class=\\\"citetext\\\" data-sentiment=\\\"Neg\\\" data-docid=\\\"32425358\\\" id=\\\"span_6\\\">WITH\\n                WRIT PETITION NO. 2888 OF 2021\\n\\n Fortpoint Automotive Mumbai Pvt. Ltd.        ....PETITIONER\\n             V/S\\n State Of Maharashtra Through Law And       ....RESPONDENT\\n Judiciary Department And Another\\n\\n                             <a href=\\\"/doc/32425358/\\\" id=\\\"a_1\\\">WITH\\n                 WRIT PETITION NO. 166 OF 2023\\n\\n Cornerstone Automobiles                      ....PETITIONER\\n             V/S\\n State Of Maharashtra                       ....RESPONDENT\\n\\n                             WITH\\n                 WRIT PETITION NO.</a> 167 OF 2023\\n\\n Cherry Corporation                           ....PETITIONER\\n            V/S\\n State Of Maharashtra                       ....RESPONDENT\\n\\n                             WITH\\n                 WRIT PETITION NO. 168 OF 2023\\n\\n\\n<span class=\\\"hidden_text\\\" id=\\\"span_7\\\">                                                                          Page 1/12</span>\\n\\n<span class=\\\"hidden_text\\\" id=\\\"span_8\\\">::: Uploaded on - 29/03/2023             ::: Downloaded on - 31/03/2023 00:49:29 :::</span>\\n  Sablok Cars                                   ....PETITIONER\\n            V/S\\n State Of Maharashtra                        ....RESPONDENT\\n\\n                             WITH\\n                 WRIT PETITION NO. 169 OF 2023\\n\\n Satish Motors(akola) Pvt. Ltd. Through Its     ....PETITIONER\\n Director Satish Shantimal Lodha\\n              V/S\\n The State Of Maharashtra Through Its Secretary\\n                                             ....RESPONDENT\\n Finance Department\\n\\n                             WITH\\n                 WRIT PETITION NO. 170 OF 2023\\n\\n Dhoot Motors Private Limited                  ....PETITIONER\\n            V/S\\n State Of Maharashtra                        ....RESPONDENT\\n\\n                             WITH\\n                 WRIT PETITION NO. 171 OF 2023\\n\\n Ratnapprabha Motors                           ....PETITIONER\\n             V/S\\n The State Of Mahrashtra Through The Secretary\\n                                            ....RESPONDENT\\n\\n                             WITH\\n                 WRIT PETITION NO. 172 OF 2023\\n\\n Sarra Motors Pvt Ltd                          ....PETITIONER\\n             V/S\\n State Of Maharashtra                        ....RESPONDENT\\n\\n                               WITH\\n\\n\\n<span class=\\\"hidden_text\\\" id=\\\"span_9\\\">                                                                           Page 2/12</span>\\n\\n<span class=\\\"hidden_text\\\" id=\\\"span_10\\\">::: Uploaded on - 29/03/2023              ::: Downloaded on - 31/03/2023 00:49:29 :::</span>\\n                  WRIT PETITION NO. 173 OF 2023\\n\\n Newaskar Automobiles                          ....PETITIONER\\n            V/S\\n State Of Maharashtra Through The Secretary ....RESPONDENT\\n\\n                             WITH\\n                 WRIT PETITION NO. 174 OF 2023\\n\\n Bhuvan Wheels Private Limited                 ....PETITIONER\\n            V/S\\n State Of Maharashtra, Through The Secretary....RESPONDENT\\n\\n                             WITH\\n                 WRIT PETITION NO. 175 OF 2023\\n\\n Dhanlaxmi Automobiles                        ....PETITIONER\\n            V/S\\n State Of Maharashtra                       ....RESPONDENT\\n\\n                             WITH\\n                 WRIT PETITION NO. 176 OF 2023\\n\\n Sablok Cars                                  ....PETITIONER\\n            V/S\\n State Of Mahrashtra Through The Secretary ....RESPONDENT\\n\\n                             WITH\\n                 WRIT PETITION NO. 177 OF 2023\\n\\n Shree Ram Bikes Scooters                     ....PETITIONER\\n            V/S\\n State Of Maharashtra                       ....RESPONDENT\\n\\n                               WITH\\n\\n\\n<span class=\\\"hidden_text\\\" id=\\\"span_11\\\">                                                                          Page 3/12</span>\\n\\n<span class=\\\"hidden_text\\\" id=\\\"span_12\\\">::: Uploaded on - 29/03/2023             ::: Downloaded on - 31/03/2023 00:49:29 :::</span>\\n                  WRIT PETITION NO. 178 OF 2023\\n\\n Fine Autolines                               ....PETITIONER\\n             V/S\\n State Of Maharashtra                       ....RESPONDENT\\n\\n                             WITH\\n                 WRIT PETITION NO. 179 OF 2023\\n\\n Salasar Wheels Private Limited Through        ....PETITIONER\\n Director Bhushan Bihani\\n             V/S\\n State Of Maharashtra Thorugh The Secretary ....RESPONDENT\\n\\n                             WITH\\n                 WRIT PETITION NO. 180 OF 2023\\n\\n Satish Motors Pvt Ltd                        ....PETITIONER\\n             V/S\\n The State Of Maharashtra                   ....RESPONDENT\\n\\n                             WITH\\n                 WRIT PETITION NO. 181 OF 2023\\n\\n Raj Auto                                     ....PETITIONER\\n            V/S\\n State Of Maharashtra                       ....RESPONDENT\\n\\n                             WITH\\n                 WRIT PETITION NO. 406 OF 2023\\n\\n Raghuvir Motor Agencies Pvt Ltd              ....PETITIONER\\n            V/S\\n State Of Maharashtra                       ....RESPONDENT\\n\\n\\n\\n<span class=\\\"hidden_text\\\" id=\\\"span_13\\\">                                                                          Page 4/12</span>\\n\\n<span class=\\\"hidden_text\\\" id=\\\"span_14\\\">::: Uploaded on - 29/03/2023             ::: Downloaded on - 31/03/2023 00:49:29 :::</span>\\n                              WITH\\n                 WRIT PETITION NO. 407 <a href=\\\"/doc/165087826/\\\" id=\\\"a_2\\\">OF 2023\\n\\n Sanya Motors Private Limited                 ....PETITIONER\\n            V/S\\n State Of Maharashtra                       ....RESPONDENT\\n\\n                             WITH\\n                 WRIT PETITION NO.</a> 408 OF 2023\\n\\n Shree Ram Bikes Scooters                     ....PETITIONER\\n            V/S\\n State Of Maharashtra                       ....RESPONDENT\\n\\n                             WITH\\n                 WRIT PETITION NO. 409 OF 2023\\n\\n Salasar Wheels Private Limited               ....PETITIONER\\n            V/S\\n State Of Maharashtra                       ....RESPONDENT\\n\\n                             WITH\\n                 WRIT PETITION NO. 410 OF 2023\\n\\n Cherry Corporation                            ....PETITIONER\\n            V/S\\n State Of Maharashtra Through The Secretary ....RESPONDENT\\n\\n                             WITH\\n                 WRIT PETITION NO. 423 OF 2023\\n\\n Kankariya Automobiles Private Limited        ....PETITIONER\\n            V/S\\n State Of Maharashtra                       ....RESPONDENT\\n\\n\\n\\n<span class=\\\"hidden_text\\\" id=\\\"span_15\\\">                                                                          Page 5/12</span>\\n\\n<span class=\\\"hidden_text\\\" id=\\\"span_16\\\">::: Uploaded on - 29/03/2023             ::: Downloaded on - 31/03/2023 00:49:29 :::</span>\\n                              WITH\\n                 WRIT PETITION NO. 478 OF 2023\\n\\n Dhanlaxmi Motors                            ....PETITIONER\\n            V/S\\n State Of Maharashtra                      ....RESPONDENT\\n\\n                             WITH\\n                 WRIT PETITION NO. 479 OF 2023\\n\\n Rironsi Automotive                          ....PETITIONER\\n             V/S\\n State Of Maharashtra                      ....RESPONDENT\\n\\n                            WITH\\n                WRIT PETITION NO. 2904 <a href=\\\"/doc/111103709/\\\" id=\\\"a_3\\\">OF 2021\\n\\n Fortpoint Automotive Mumbai Pvt Ltd         ....PETITIONER\\n             V/S\\n The State Of Maharashtra And Anr</a>          ....RESPONDENT\\n\\n                             WITH\\n                 WRIT PETITION NO. 446 OF 2022\\n\\n Sap Holdings And Leasing Pvt. Ltd.          ....PETITIONER\\n             V/S\\n The State Of Maharashtra And 2 Ors.       ....RESPONDENT\\n\\n                            WITH\\n                WRIT PETITION NO. 1749 OF 2021\\n\\n Metro Motors Auto Hangar Division           ....PETITIONER\\n            V/S\\n State Of Maharashtra And 3 Ors.           ....RESPONDENT\\n\\n\\n\\n<span class=\\\"hidden_text\\\" id=\\\"span_17\\\">                                                                         Page 6/12</span>\\n\\n<span class=\\\"hidden_text\\\" id=\\\"span_18\\\">::: Uploaded on - 29/03/2023            ::: Downloaded on - 31/03/2023 00:49:29 :::</span>\\n                             WITH\\n                WRIT PETITION NO. 2834 OF 2021\\n\\n Fortpoint Automotive (cars) Pvt. Ltd.        ....PETITIONER\\n             V/S\\n State Bank Of Maharashtra And Anr          ....RESPONDENT\\n\\n                            WITH\\n                WRIT PETITION NO. 4053 OF 2022\\n\\n Modi Car Agencies Pvt. Ltd.                  ....PETITIONER\\n             V/S\\n The State Of Maharashtra And 2 Others      ....RESPONDENT\\n\\n                            WITH\\n                WRIT PETITION NO. 4055 OF 2022\\n\\n Krishiv Motors Pvt Ltd                       ....PETITIONER\\n             V/S\\n The State Of Maharashtra And 2 Ors         ....RESPONDENT\\n\\n                             WITH\\n                 WRIT PETITION NO. 439 OF 2022\\n\\n Sap Holdings And Leasing Pvt. Ltd.           ....PETITIONER\\n             V/S\\n The State Of Maharashtra And 2 Ors         ....RESPONDENT\\n\\n                        WITH\\n        WRIT PETITION LODGING NO. 6743 OF 2022\\n\\n Ishna Motors                                 ....PETITIONER\\n            V/S\\n State Of Maharashtra And Anr.              ....RESPONDENT\\n\\n\\n\\n<span class=\\\"hidden_text\\\" id=\\\"span_19\\\">                                                                          Page 7/12</span>\\n\\n<span class=\\\"hidden_text\\\" id=\\\"span_20\\\">::: Uploaded on - 29/03/2023             ::: Downloaded on - 31/03/2023 00:49:29 :::</span>\\n                             WITH\\n                WRIT PETITION NO. 3727 <a href=\\\"/doc/77312902/\\\" id=\\\"a_4\\\">OF 2021\\n\\n Krishiv Motors Pvt. Ltd.                     ....PETITIONER\\n             V/S\\n The State Of Maharashtra And</a> 2 Ors.        ....RESPONDENT\\n\\n                            WITH\\n                WRIT PETITION NO. 2561 OF 2021\\n\\n S C Auto Agencies Pvt Ltd                    ....PETITIONER\\n             V/S\\n The State Of Maharashtra And 2 Ors         ....RESPONDENT\\n\\n                        WITH\\n        WRIT PETITION LODGING NO. 3658 OF 2023\\n\\n Kifs Motors Private Limited                  ....PETITIONER\\n             V/S\\n State Of Maharashtra                       ....RESPONDENT\\n\\n                             WITH\\n                  WRIT PETITION NO. 56 <a href=\\\"/doc/146202757/\\\" id=\\\"a_5\\\">OF 2023\\n\\n Infinity Autolinks Private Limited           ....PETITIONER\\n              V/S\\n State Of Maharashtra And</a> 2 Ors.            ....RESPONDENT\\n\\n                       WITH\\n       WRIT PETITION LODGING NO. 24664 OF 2022\\n\\n Spectra Motors Limited                       ....PETITIONER\\n            V/S\\n State Of Maharashtra And 2 Ors             ....RESPONDENT\\n\\n\\n\\n<span class=\\\"hidden_text\\\" id=\\\"span_21\\\">                                                                          Page 8/12</span>\\n\\n<span class=\\\"hidden_text\\\" id=\\\"span_22\\\">::: Uploaded on - 29/03/2023             ::: Downloaded on - 31/03/2023 00:49:29 :::</span>\\n                             WITH\\n                WRIT PETITION NO. 2858 OF 2021\\n\\n Fortpoint Automotive Private Limited        ....PETITIONER\\n             V/S\\n The State Of Maharashtra And Anr.         ....RESPONDENT\\n\\n                            WITH\\n                WRIT PETITION NO. 2877 <a href=\\\"/doc/12976213/\\\" id=\\\"a_6\\\">OF 2021\\n\\n Fortpoint Automotive Private Limited        ....PETITIONER\\n             V/S\\n The State Of Maharashtra And Anr</a>          ....RESPONDENT\\n\\n                             WITH\\n                 WRIT PETITION NO. 322 OF 2022\\n\\n Fortpoint Automotive Pvt.ltd.</span></span></span></span></span></span>               <span class=\\\"citetext\\\" data-sentiment=\\\"PARTY\\\" data-docid=\\\"13206390\\\" id=\\\"span_23\\\"><span class=\\\"citetext\\\" data-sentiment=\\\"PARTY\\\" data-docid=\\\"113152717\\\" id=\\\"span_24\\\"><span class=\\\"citetext\\\" data-sentiment=\\\"PARTY\\\" data-docid=\\\"24225619\\\" id=\\\"span_25\\\"><span class=\\\"citetext\\\" data-sentiment=\\\"PARTY\\\" data-docid=\\\"165087826\\\" id=\\\"span_26\\\">...<a href=\\\"/doc/165087826/\\\" id=\\\"a_7\\\">.PETITIONER\\n             V/S\\n State Of Maharashtra And Anr.             ....RESPONDENT\\n\\n                            WITH\\n                WRIT PETITION NO.</a> 2161 <a href=\\\"/doc/24225619/\\\" id=\\\"a_8\\\">OF 2021\\n\\n Sharayu Autolinks Pvt. Ltd.                 ....PETITIONER\\n             V/S\\n The State Of Maharashtra And</a> 2 Ors.       ....RESPONDENT\\n\\n                            WITH\\n                WRIT PETITION NO. 2387 OF 2021\\n\\n Vcm Agencies Pvt Ltd                        ....PETITIONER\\n             V/S\\n The State Of Maharashtra And 2 Ors        ....RESPONDENT\\n\\n\\n\\n<span class=\\\"hidden_text\\\" id=\\\"span_27\\\">                                                                         Page 9/12</span>\\n\\n<span class=\\\"hidden_text\\\" id=\\\"span_28\\\">::: Uploaded on - 29/03/2023            ::: Downloaded on - 31/03/2023 00:49:29 :::</span>\\n                             WITH\\n                WRIT PETITION NO. 2194 OF 2021\\n\\n Modi Motors Agencies Pvt. Ltd.               ....PETITIONER\\n             V/S\\n The State Of Maharashtra And 2 Ors         ....RESPONDENT\\n\\n                            WITH\\n                WRIT PETITION NO. 5231 OF 2022\\n\\n Vidarbha Automobile Dealers Association       ....PETITIONER\\n Through Achal A Gandhi\\n            V/S\\n State Of Maharashtra Through The Secretary ....RESPONDENT\\n\\n                            WITH\\n                WRIT PETITION NO. 2840 <a href=\\\"/doc/113152717/\\\" id=\\\"a_9\\\">OF 2021\\n\\n Fortpoint Automotive (cars) Pvt. Ltd.        ....PETITIONER\\n             V/S\\n State Of Maharashtra And Another</a>           ....RESPONDENT\\n\\n                            WITH\\n                WRIT PETITION NO. 3792 OF 2021\\n\\n Ishna Motors                                 ....PETITIONER\\n            V/S\\n State Of Maharashtra And Anr.              ....RESPONDENT\\n\\n                        WITH\\n        WRIT PETITION LODGING NO. 7052 <a href=\\\"/doc/13206390/\\\" id=\\\"a_10\\\">OF 2022\\n\\n Modi Car Agencies Pvt Ltd                    ....PETITIONER\\n             V/S\\n The State Of Maharashtra And</a> 2 Ors         ....RESPONDENT\\n\\n\\n<span class=\\\"hidden_text\\\" id=\\\"span_29\\\">                                                                         Page 10/12</span>\\n\\n<span class=\\\"hidden_text\\\" id=\\\"span_30\\\">::: Uploaded on - 29/03/2023             ::: Downloaded on - 31/03/2023 00:49:29 :::</span>\\n  Mr. Ratan Samal a/w Mr.Manohar Samal for the Petitioners in\\n WP Nos. 2161/2021, 446/2022 and 439/2022.\\n Ms.Swatantri Waghmare for Res No.1 in WP No.2834/2021.\\n Mr.Bharat Raichandani a/w Ms.Juhi Bahirwani i/b M/s Veritas\\n Legal for the Petitioners in WP No.1749/2021.\\n Ms.Nikita Badheka i/by Ms.Lata Nagal, Advocates for the\\n Petitioners in WPLs No.24664/2022 and 56/2023.\\n Mr.Bharat Raichandani a/w Mr.Rishabh Jain i/b\\n M/s UBR Legal for the Petitioners in WP No.3792/2021\\n and WPL No.6743/2022, WPL 7052/2022.\\n Mr.V.A.Sonpal, Special Counsel with Ms.Jyoti Chavan, AGP\\n for the State in WP Nos.2194/2021, 2387/2021, 4053/2022,\\n 4055/2022.</span></span></span></span>\\n</p><p data-structure=\\\"Precedent\\\" id=\\\"p_2\\\"> Mr.V.A.Sonpal, Special Counsel a/w\\n Ms.P.H.Kantharia, GP for the State in WP No.2512/2021.\\n Mr.V.A.Sonpal, Special Counsel a/w Mr.Hemant Haryan, AGP\\n for the State in WP No.3792/2021,WPL No.6743/2022.\\n Mr.V.A.Sonpal, Special Counsel a/w Mr.Himanshu Takke,\\n AGP\\n for the State in WP No.2561/2021, 3727/2021.\\n Ms.Jyoti Chavan, AGP for the State in WP Nos.446/2022,\\n 439/2022.\\n</p><p data-structure=\\\"PetArg\\\" id=\\\"p_3\\\"> Mr.Himanshu Takke, AGP for the State in WPL\\n Nos.7052/2022, 24664/2022.\\n Mr.Vaibhav Shukla a/w Ms.Ira Mishra i/b\\n Mr. Prabhakar Jadhav, for the Petitioners in WPs No.2840/2021,\\n 2877/2021, 2834/2021, 1749/2021, 322/2021, 2858/2021,\\n 2904/2021, 2888/2021, 2834/2021.\\n Mr.Shashikant Gaikwad i/by Mr.Sharad Bhattad for the\\n Petitioner in WP No.5231/2022, 3686/2020, 3658/2020.\\n</p>\\n\\n\\n<p data-structure=\\\"Conclusion\\\" id=\\\"p_4\\\">        CORAM :                HON&#x27;BLE SHRI JUSTICE NITIN JAMDAR &amp;\\n                               HON&#x27;BLE SHRI JUSTICE ABHAY AHUJA, JJ\\n        DATE :                 29th March, 2023\\n\\n\\n<span class=\\\"hidden_text\\\" id=\\\"span_31\\\">                                                                                  Page 11/12</span>\\n\\n<span class=\\\"hidden_text\\\" id=\\\"span_32\\\">::: Uploaded on - 29/03/2023                      ::: Downloaded on - 31/03/2023 00:49:29 :::</span>\\n  P.C. :\\n</p><blockquote id=\\\"blockquote_1\\\">     S. O. to 12/04/2023 ( at 2.30 pm).\\n</blockquote>\\n\\n\\n<blockquote id=\\\"blockquote_2\\\">                                          ( ASSOCIATE )\\n\\n\\n\\n\\n<span class=\\\"hidden_text\\\" id=\\\"span_33\\\">                                                                           Page 12/12</span>\\n\\n<span class=\\\"hidden_text\\\" id=\\\"span_34\\\">::: Uploaded on - 29/03/2023               ::: Downloaded on - 31/03/2023 00:49:29 :::</span>\\n </blockquote>\",\"numcites\":9,\"numcitedby\":64,\"docsource\":\"Bombay High Court\",\"citetid\":194020500,\"divtype\":\"judgments\",\"relatedqs\":[{\"value\":\"FORTPOINT AUTOMOTIVE \",\"formInput\":\"FORTPOINT%20AUTOMOTIVE%20\"},{\"value\":\"automobile\",\"formInput\":\"automobile\"},{\"value\":\"automotive\",\"formInput\":\"automotive\"},{\"value\":\"modi\",\"formInput\":\"modi\"}],\"courtcopy\":true,\"query_alert\":null,\"agreement\":false}",
  "metadata": "{\"tid\":194020500,\"publishdate\":\"2023-03-29\",\"doctype\":\"Bombay High Court\",\"relurl\":\"bombay/2023-03-29/WPL-7052-2022\",\"caseno\":\"WPL/7052/2022\\n(1) 29/03/2023\",\"numcites\":9,\"numcitedby\":64,\"title\":\"Modi Car Agencies Pvt Ltd vs The State Of Maharashtra And 2 Ors on 29 March, 2023\"}"
}